redisify/__init__.py
redisify/config.py
redisify/serializer.py
redisify/distributed/limiter.py
redisify/distributed/lock.py
redisify/distributed/semaphore.py
redisify/structures/dict.py
redisify/structures/list.py
redisify/structures/queue.py
redisify/structures/set.py
redisify-0.2.0.dist-info/licenses/LICENSE
redisify-0.2.0.dist-info/METADATA
redisify-0.2.0.dist-info/WHEEL
redisify-0.2.0.dist-info/top_level.txt
redisify-0.2.0.dist-info/RECORD
