Metadata-Version: 2.4
Name: redisify
Version: 0.2.0
Summary: Redisify is a lightweight Python library that provides Redis-backed data structures like dicts, queues, locks, and semaphores, designed for distributed systems.
Author-email: Lei Zhang <jameszhang2880@gmail.com>
License: MIT
Classifier: Programming Language :: Python :: 3
Classifier: License :: OSI Approved :: MIT License
Classifier: Operating System :: OS Independent
Requires-Python: >=3.10
License-File: LICENSE
Requires-Dist: redis
Requires-Dist: dill
Provides-Extra: test
Requires-Dist: pytest>=7.0; extra == "test"
Requires-Dist: pytest-asyncio>=0.20.0; extra == "test"
Dynamic: license-file
